sensi/__init__.py
sensi/database/__init__.py
sensi/database/dataset.db
sensi/database/models.py
sensi/database/query.py
sensi/resources/__init__.py
sensi/resources/nltk_data/corpora/stopwords/README
sensi/resources/nltk_data/corpora/stopwords/arabic
sensi/resources/nltk_data/corpora/stopwords/azerbaijani
sensi/resources/nltk_data/corpora/stopwords/danish
sensi/resources/nltk_data/corpora/stopwords/dutch
sensi/resources/nltk_data/corpora/stopwords/english
sensi/resources/nltk_data/corpora/stopwords/finnish
sensi/resources/nltk_data/corpora/stopwords/french
sensi/resources/nltk_data/corpora/stopwords/german
sensi/resources/nltk_data/corpora/stopwords/greek
sensi/resources/nltk_data/corpora/stopwords/hungarian
sensi/resources/nltk_data/corpora/stopwords/indonesian
sensi/resources/nltk_data/corpora/stopwords/italian
sensi/resources/nltk_data/corpora/stopwords/kazakh
sensi/resources/nltk_data/corpora/stopwords/nepali
sensi/resources/nltk_data/corpora/stopwords/norwegian
sensi/resources/nltk_data/corpora/stopwords/portuguese
sensi/resources/nltk_data/corpora/stopwords/romanian
sensi/resources/nltk_data/corpora/stopwords/russian
sensi/resources/nltk_data/corpora/stopwords/slovene
sensi/resources/nltk_data/corpora/stopwords/spanish
sensi/resources/nltk_data/corpora/stopwords/swedish
sensi/resources/nltk_data/corpora/stopwords/tajik
sensi/resources/nltk_data/corpora/stopwords/turkish
sensi/resources/nltk_data/corpora/stopwords.zip
sensi/resources/nltk_data/tokenizers/punkt/PY3/README
sensi/resources/nltk_data/tokenizers/punkt/PY3/czech.pickle
sensi/resources/nltk_data/tokenizers/punkt/PY3/danish.pickle
sensi/resources/nltk_data/tokenizers/punkt/PY3/dutch.pickle
sensi/resources/nltk_data/tokenizers/punkt/PY3/english.pickle
sensi/resources/nltk_data/tokenizers/punkt/PY3/estonian.pickle
sensi/resources/nltk_data/tokenizers/punkt/PY3/finnish.pickle
sensi/resources/nltk_data/tokenizers/punkt/PY3/french.pickle
sensi/resources/nltk_data/tokenizers/punkt/PY3/german.pickle
sensi-1.0.14.dist-info/LICENSE
sensi-1.0.14.dist-info/METADATA
sensi-1.0.14.dist-info/WHEEL
sensi-1.0.14.dist-info/RECORD
