Metadata-Version: 2.1
Name: sensi
Version: 1.0.14
Summary: Naive-Bayes based sentiment analysis library for the Indonesian Language.
Home-page: https://github.com/GazDuckington/sensi
License: MIT
Keywords: NLP,Bahasa,Indonesia,Sentimen,Analisis
Author: GazDuckington
Author-email: dianghazy@protonmail.com
Requires-Python: >=3.11,<4.0
Classifier: Intended Audience :: Developers
Classifier: Intended Audience :: Information Technology
Classifier: Intended Audience :: Science/Research
Classifier: License :: OSI Approved :: MIT License
Classifier: Natural Language :: Indonesian
Classifier: Operating System :: OS Independent
Classifier: Programming Language :: Python
Classifier: Programming Language :: Python :: 3
Classifier: Programming Language :: Python :: 3.11
Classifier: Programming Language :: Python :: 3.12
Classifier: Topic :: Scientific/Engineering :: Artificial Intelligence
Classifier: Topic :: Software Development :: Libraries :: Python Modules
Classifier: Topic :: Text Processing :: Linguistic
Requires-Dist: SQLAlchemy[asyncio] (>=1.4.45,<3.0.0)
Requires-Dist: aiosqlite (>=0.18,<0.20)
Requires-Dist: bahasa (>=1.0.1,<2.0.0)
Requires-Dist: nltk (>=3.8,<4.0)
Requires-Dist: numpy (>=1.24.1,<2.0.0)
Requires-Dist: pandas (>=1.5.2,<3.0.0)
Project-URL: Repository, https://github.com/GazDuckington/sensi
